modoboa_postfix_autoreply/__init__.py
modoboa_postfix_autoreply/apps.py
modoboa_postfix_autoreply/factories.py
modoboa_postfix_autoreply/forms.py
modoboa_postfix_autoreply/handlers.py
modoboa_postfix_autoreply/known_problems.py
modoboa_postfix_autoreply/models.py
modoboa_postfix_autoreply/modo_extension.py
modoboa_postfix_autoreply/serializers.py
modoboa_postfix_autoreply/tests.py
modoboa_postfix_autoreply/urls_api.py
modoboa_postfix_autoreply/views.py
modoboa_postfix_autoreply/viewsets.py
modoboa_postfix_autoreply/locale/cs_CZ/LC_MESSAGES/django.mo
modoboa_postfix_autoreply/locale/cs_CZ/LC_MESSAGES/django.po
modoboa_postfix_autoreply/locale/de/LC_MESSAGES/django.mo
modoboa_postfix_autoreply/locale/de/LC_MESSAGES/django.po
modoboa_postfix_autoreply/locale/el_GR/LC_MESSAGES/django.mo
modoboa_postfix_autoreply/locale/el_GR/LC_MESSAGES/django.po
modoboa_postfix_autoreply/locale/en/LC_MESSAGES/django.mo
modoboa_postfix_autoreply/locale/en/LC_MESSAGES/django.po
modoboa_postfix_autoreply/locale/es/LC_MESSAGES/django.mo
modoboa_postfix_autoreply/locale/es/LC_MESSAGES/django.po
modoboa_postfix_autoreply/locale/fr/LC_MESSAGES/django.mo
modoboa_postfix_autoreply/locale/fr/LC_MESSAGES/django.po
modoboa_postfix_autoreply/locale/it/LC_MESSAGES/django.mo
modoboa_postfix_autoreply/locale/it/LC_MESSAGES/django.po
modoboa_postfix_autoreply/locale/ja_JP/LC_MESSAGES/django.mo
modoboa_postfix_autoreply/locale/ja_JP/LC_MESSAGES/django.po
modoboa_postfix_autoreply/locale/nl_NL/LC_MESSAGES/django.mo
modoboa_postfix_autoreply/locale/nl_NL/LC_MESSAGES/django.po
modoboa_postfix_autoreply/locale/pl_PL/LC_MESSAGES/django.mo
modoboa_postfix_autoreply/locale/pl_PL/LC_MESSAGES/django.po
modoboa_postfix_autoreply/locale/pt_BR/LC_MESSAGES/django.mo
modoboa_postfix_autoreply/locale/pt_BR/LC_MESSAGES/django.po
modoboa_postfix_autoreply/locale/pt_PT/LC_MESSAGES/django.mo
modoboa_postfix_autoreply/locale/pt_PT/LC_MESSAGES/django.po
modoboa_postfix_autoreply/locale/ro_RO/LC_MESSAGES/django.mo
modoboa_postfix_autoreply-1.8.1.dist-info/LICENSE
modoboa_postfix_autoreply-1.8.1.dist-info/METADATA
modoboa_postfix_autoreply-1.8.1.dist-info/WHEEL
modoboa_postfix_autoreply-1.8.1.dist-info/top_level.txt
modoboa_postfix_autoreply-1.8.1.dist-info/RECORD
