Metadata-Version: 2.1
Name: modoboa-postfix-autoreply
Version: 1.8.1
Summary: Away message editor for Modoboa (postfix compatible)
Home-page: http://modoboa.org/
Author: Antoine Nguyen
Author-email: tonio@ngyn.org
License: MIT
Keywords: email postfix
Classifier: Development Status :: 5 - Production/Stable
Classifier: Environment :: Web Environment
Classifier: Framework :: Django :: 2.2
Classifier: Intended Audience :: System Administrators
Classifier: License :: OSI Approved :: MIT License
Classifier: Operating System :: OS Independent
Classifier: Programming Language :: Python :: 3
Classifier: Programming Language :: Python :: 3.5
Classifier: Programming Language :: Python :: 3.6
Classifier: Programming Language :: Python :: 3.7
Classifier: Topic :: Communications :: Email
Classifier: Topic :: Internet :: WWW/HTTP
License-File: LICENSE
Requires-Dist: pytz
Requires-Dist: django-filter ==23.5
